mlm/__init__.py
mlm/__main__.py
mlm/build.py
mlm/config.py
mlm/g_dl.py
mlm/initial_setup.py
mlm/media.py
mlm/options.py
mlm/prompts.py
mlm/search.py
mlm/system.py
mlm/utils.py
py_mlm-0.0.17.dist-info/LICENSE
py_mlm-0.0.17.dist-info/METADATA
py_mlm-0.0.17.dist-info/WHEEL
py_mlm-0.0.17.dist-info/entry_points.txt
py_mlm-0.0.17.dist-info/top_level.txt
py_mlm-0.0.17.dist-info/RECORD
