Metadata-Version: 2.1
Name: py-mlm
Version: 0.0.17
Summary: mlm - Manga Library Manager. Local, and simple method for reading and tracking manga.
License: GNU General Public License v3 (GPLv3)
Project-URL: repository, https://codeberg.org/johndovern/mlm
Keywords: zathura,sioyek
License-File: LICENSE
Requires-Dist: python-magic
Requires-Dist: loadconf
Requires-Dist: promptx>=0.0.5
